dagster_static/__init__.py
dagster_static/traits.py
dagster_static-0.1.0.dist-info/licenses/LICENSE
dagster_static-0.1.0.dist-info/METADATA
dagster_static-0.1.0.dist-info/WHEEL
dagster_static-0.1.0.dist-info/top_level.txt
dagster_static-0.1.0.dist-info/RECORD
