Metadata-Version: 2.4
Name: dagster-static
Version: 0.1.0
Summary: Trait-based static validation system for Dagster assets
Author-email: Boris Resnick <boris.resnick@gmail.com>
Maintainer-email: Boris Resnick <boris.resnick@gmail.com>
Keywords: dagster,data-pipeline,static-validation,trait-system,type-checking
Classifier: Development Status :: 4 - Beta
Classifier: Intended Audience :: Developers
Classifier: Operating System :: OS Independent
Classifier: Programming Language :: Python :: 3
Classifier: Programming Language :: Python :: 3.13
Classifier: Topic :: Software Development :: Libraries :: Python Modules
Classifier: Topic :: Scientific/Engineering
Requires-Python: >=3.13
License-File: LICENSE
Requires-Dist: dagster>=1.12.0
Dynamic: license-file
